jiren/__init__.py
jiren/_version.py
jiren/cli.py
jiren/template.py
jiren-0.7.5.dist-info/METADATA
jiren-0.7.5.dist-info/WHEEL
jiren-0.7.5.dist-info/entry_points.txt
jiren-0.7.5.dist-info/licenses/LICENSE
jiren-0.7.5.dist-info/RECORD
