Metadata-Version: 2.1
Name: jiren
Version: 0.7.5
Summary: jinja2 template renderer
Project-URL: Homepage, https://github.com/speg03/jiren
Project-URL: Repository, https://github.com/speg03/jiren
Author-email: Takahiro Yano <speg03@gmail.com>
License-File: LICENSE
Keywords: jinja2,preprocessing,render,template,text
Classifier: Development Status :: 4 - Beta
Classifier: Environment :: Console
Classifier: Intended Audience :: Developers
Classifier: License :: OSI Approved :: MIT License
Classifier: Operating System :: OS Independent
Classifier: Programming Language :: Python :: 3.7
Classifier: Programming Language :: Python :: 3.8
Classifier: Programming Language :: Python :: 3.9
Classifier: Programming Language :: Python :: 3.10
Classifier: Topic :: Software Development :: Libraries :: Python Modules
Classifier: Topic :: Software Development :: Pre-processors
Requires-Python: >=3.7
Requires-Dist: jinja2>=2.11
Requires-Dist: pyyaml>=5.3
Provides-Extra: tests
Requires-Dist: pytest; extra == 'tests'
Requires-Dist: pytest-cov; extra == 'tests'
